MANIFEST.in
setup.py
cap_schemas.egg-info/PKG-INFO
cap_schemas.egg-info/SOURCES.txt
cap_schemas.egg-info/dependency_links.txt
cap_schemas.egg-info/requires.txt
cap_schemas.egg-info/top_level.txt
capschemas/__init__.py
capschemas/__init__.pyc
capschemas/packtivity/packtivity-schema.json
capschemas/packtivity/environment/docker-enc-schema.json
capschemas/packtivity/environment/localproc-schema.json
capschemas/packtivity/environment/manual-instructions-env-schema.json
capschemas/packtivity/environment/noop-env-schema.json
capschemas/packtivity/process/manual-instructions-proc-schema.json
capschemas/packtivity/process/scriptproc-schema.json
capschemas/packtivity/process/stringinterp-schema.json
capschemas/packtivity/publisher/constant-pub-schema.json
capschemas/packtivity/publisher/fromglob-pub-schema.json
capschemas/packtivity/publisher/frompar-pub-schema.json
capschemas/packtivity/publisher/fromyaml-pub-schema.json
capschemas/packtivity/publisher/manual-instructions-pub-schema.json
capschemas/yadage/stage-schema.json
capschemas/yadage/workflow-schema.json
capschemas/yadage/predicates/jsonpathready-schema.json
capschemas/yadage/scheduler/multistep-stage-schema.json
capschemas/yadage/scheduler/parameterselection.json
capschemas/yadage/scheduler/singlestep-stage-schema.json