Metadata-Version: 1.0
Name: cap-schemas
Version: 0.4.5
Summary: schemas for analysis preservation
Home-page: UNKNOWN
Author: Lukas Heinrich
Author-email: lukas.heinrich@gmail.com
License: UNKNOWN
Platform: UNKNOWN
